{
    "1": {
        "speaker": "PANDA",
        "character": "やっと着いた",
        "definition": "I'm finally here!",
        "timestamp": "0:01:44",
        "audio": "/audio/15/0.01.44.mp3"
    },
    "2": {
        "speaker": "PANDA",
        "character": "近道しようとしたら　雑草がすごくて迷ちゃったよ",
        "definition": "I was trying to take a shortcut, but the weeds were so thick that I got lost.",
        "timestamp": "0:01:49",
        "audio": "/audio/15/0.01.49.mp3"
    },
    "3": {
        "speaker": "SASAKO",
        "character": "そうなの　迷ちゃうお客さんもいるみたい",
        "definition": "Yes, I've heard other customers have gotten lost, too.",
        "timestamp": "0:01:54",
        "audio": "/audio/15/0.01.54.mp3"
    },
    "4": {
        "speaker": "PANDA",
        "character": "隣なのに家から20分かかちゃったよ",
        "definition": "I live next door, but it took me twenty minutes to get here. These weeds are thick. Let's sit inside.",
        "timestamp": "0:01:57",
        "audio": "/audio/15/0.01.57.mp3"
    },
    "5": {
        "speaker": "POLAR BEAR",
        "character": "よし　やろう",
        "definition": "Okay, let's do it! What are you doing, Polar Bear?",
        "timestamp": "0:02:07",
        "audio": "/audio/15/0.02.07.mp3"
    },
    "6": {
        "speaker": "POLAR BEAR",
        "character": "テラスで風を感じながら キンキンに冷したミントティーを飲んでる",
        "definition": "I'm enjoying the cool breeze as I sit on the terrace drinking an ice cold mint tea.",
        "timestamp": "0:02:23",
        "audio": "/audio/15/0.02.23.mp3"
    },
    "7": {
        "speaker": "PENGUIN",
        "character": "そうじゃなくて",
        "definition": "That's not what I meant.",
        "timestamp": "0:02:29",
        "audio": "/audio/15/0.02.29.mp3"
    },
    "8": {
        "speaker": "PENGUIN",
        "character": "なんで僕に君の店の雑草取りさせて",
        "definition": "Why am I weeding your café's lawn",
        "timestamp": "0:02:31",
        "audio": "/audio/15/0.02.31.mp3"
    },
    "9": {
        "speaker": "PENGUIN",
        "character": "君がテラスをすすんでるの",
        "definition": "while you're sitting there, drinking tea?!",
        "timestamp": "0:02:34",
        "audio": "/audio/15/0.02.34.mp3"
    },
    "10": {
        "speaker": "POLAR BEAR",
        "character": "僕は普通寒いところにいるでしょう",
        "definition": "I usually live where it's cold.",
        "timestamp": "0:02:36",
        "audio": "/audio/15/0.02.36.mp3"
    },
    "11": {
        "speaker": "PENGUIN",
        "character": "僕もだよ",
        "definition": "So do I!",
        "timestamp": "0:02:39",
        "audio": "/audio/15/0.02.39.mp3"
    },
    "12": {
        "speaker": "PENGUIN",
        "character": "真夏に雑草取りをするペンギンなんて どこの世界にいるの",
        "definition": "In what world is there a penguin who weeds in the middle of summer?!",
        "timestamp": "0:02:40",
        "audio": "/audio/15/0.02.40.mp3"
    },
    "13": {
        "speaker": "LLAMA",
        "character": "ごちそうさまでした",
        "definition": "Thank you for the meal.",
        "timestamp": "0:02:44",
        "audio": "/audio/15/0.02.44.mp3"
    },
    "14": {
        "speaker": "LLAMA",
        "character": "では",
        "definition": "I'll be seeing you.",
        "timestamp": "0:02:46",
        "audio": "/audio/15/0.02.46.mp3"
    },
    "15": {
        "speaker": "PENGUIN",
        "character": "らまさん　どこ行くの",
        "definition": "Mr. Llama, where are you going?",
        "timestamp": "0:02:47",
        "audio": "/audio/15/0.02.47.mp3"
    },
    "16": {
        "speaker": "LLAMA",
        "character": "もう食べられないんで　失礼しようかなって",
        "definition": "I can't eat anymore, so I figured I'd leave.",
        "timestamp": "0:02:50",
        "audio": "/audio/15/0.02.50.mp3"
    },
    "17": {
        "speaker": "PENGUIN",
        "character": "ちょっと待って　なんで帰ちゃうの",
        "definition": "Wait a minute. Why are you going home?",
        "timestamp": "0:02:54",
        "audio": "/audio/15/0.02.54.mp3"
    },
    "18": {
        "speaker": "",
        "character": "僕たちの雑草取り始まったばかりでしょう",
        "definition": "We just started weeding.",
        "timestamp": "0:02:56",
        "audio": "/audio/15/0.02.56.mp3"
    },
    "19": {
        "speaker": "LLAMA",
        "character": "けど　もうお腹いっぱいですよ",
        "definition": "But I'm full.",
        "timestamp": "0:03:00",
        "audio": "/audio/15/0.03.00.mp3"
    },
    "20": {
        "speaker": "PENGUIN",
        "character": "雑草取りって　そういうことじゃないでしょう",
        "definition": "But weeding is much more than that.",
        "timestamp": "0:03:02",
        "audio": "/audio/15/0.03.02.mp3"
    },
    "21": {
        "speaker": "PENGUIN",
        "character": "もうちょっと頑張ろうよ",
        "definition": "Let's try a little harder.",
        "timestamp": "0:03:05",
        "audio": "/audio/15/0.03.05.mp3"
    },
    "22": {
        "speaker": "LLAMA",
        "character": "僕　もうお腹はじけちゃいますよ",
        "definition": "But... my stomach will burst.",
        "timestamp": "0:03:08",
        "audio": "/audio/15/0.03.08.mp3"
    },
    "23": {
        "speaker": "PENGUIN",
        "character": "そうじゃなくて",
        "definition": "That's not what I meant... Um... is there any way to weedthat doesn't involve eating?",
        "timestamp": "0:03:12",
        "audio": "/audio/15/0.03.12.mp3"
    },
    "24": {
        "speaker": "LLAMA",
        "character": "そうでしたか　ちょっと考えてみます",
        "definition": "Oh, I see. Let me think.",
        "timestamp": "0:03:19",
        "audio": "/audio/15/0.03.19.mp3"
    },
    "25": {
        "speaker": "PENGUIN",
        "character": "寝てる",
        "definition": "Are you asleep?",
        "timestamp": "0:03:29",
        "audio": "/audio/15/0.03.29.mp3"
    },
    "26": {
        "speaker": "LLAMA",
        "character": "起きてますよ",
        "definition": "I'm awake.",
        "timestamp": "0:03:31",
        "audio": "/audio/15/0.03.31.mp3"
    },
    "27": {
        "speaker": "PENGUIN",
        "character": "寝てたでしょう",
        "definition": "You were totally asleep.",
        "timestamp": "0:03:32",
        "audio": "/audio/15/0.03.32.mp3"
    },
    "28": {
        "speaker": "POLAR BEAR",
        "character": "ミントティー　どう？",
        "definition": "Would you like some mint tea?",
        "timestamp": "0:03:34",
        "audio": "/audio/15/0.03.34.mp3"
    },
    "29": {
        "speaker": "LLAMA",
        "character": "あ　いただきます",
        "definition": "Oh, thank you.",
        "timestamp": "0:03:36",
        "audio": "/audio/15/0.03.36.mp3"
    },
    "30": {
        "speaker": "PENGUIN",
        "character": "もう　皆　頑張ろうよ",
        "definition": "Come on, guys. Let's work harder!",
        "timestamp": "0:03:38",
        "audio": "/audio/15/0.03.38.mp3"
    },
    "31": {
        "speaker": "KOALA",
        "character": "頑張りたいんだけど　僕ユーカリしか食べられなっくて",
        "definition": "I'd like to try harder, but I can only eat eucalyptus.",
        "timestamp": "0:03:41",
        "audio": "/audio/15/0.03.41.mp3"
    },
    "32": {
        "speaker": "PENGUIN",
        "character": "だから　食べない方法もあるんじゃないかな",
        "definition": "I'm saying... there are other ways to weedthat don't involve eating.",
        "timestamp": "0:03:47",
        "audio": "/audio/15/0.03.47.mp3"
    },
    "33": {
        "speaker": "PANDA",
        "character": "ペンギンさん",
        "definition": "Mr. Penguin.",
        "timestamp": "0:03:51",
        "audio": "/audio/15/0.03.51.mp3"
    },
    "34": {
        "speaker": "PANDA",
        "character": "変な形の石拾った",
        "definition": "I found a weird shaped rock.",
        "timestamp": "0:03:55",
        "audio": "/audio/15/0.03.55.mp3"
    },
    "35": {
        "speaker": "PENGUIN",
        "character": "要らないの　その報告は　雑草取ろう",
        "definition": "We didn't need to know that. Let's get rid of some weeds.",
        "timestamp": "0:03:58",
        "audio": "/audio/15/0.03.58.mp3"
    },
    "36": {
        "speaker": "SASAKO",
        "character": "ペンギンさん",
        "definition": "Mr. Penguin.",
        "timestamp": "0:04:02",
        "audio": "/audio/15/0.04.02.mp3"
    },
    "37": {
        "speaker": "PENGUIN",
        "character": "笹子さん　それは？",
        "definition": "What is that, Miss Sasako?",
        "timestamp": "0:04:05",
        "audio": "/audio/15/0.04.05.mp3"
    },
    "38": {
        "speaker": "SASAKO",
        "character": "土偶です",
        "definition": "It's a clay figure.",
        "timestamp": "0:04:08",
        "audio": "/audio/15/0.04.08.mp3"
    },
    "39": {
        "speaker": "SASAKO",
        "character": "拾いました",
        "definition": "I found it.",
        "timestamp": "0:04:09",
        "audio": "/audio/15/0.04.09.mp3"
    },
    "40": {
        "speaker": "SASAKO",
        "character": "要らない報告でした",
        "definition": "I guess you didn't need to know that.",
        "timestamp": "0:04:12",
        "audio": "/audio/15/0.04.12.mp3"
    },
    "41": {
        "speaker": "PENGUIN",
        "character": "何　この庭",
        "definition": "What is with this yard?",
        "timestamp": "0:04:15",
        "audio": "/audio/15/0.04.15.mp3"
    },
    "42": {
        "speaker": "POLAR BEAR",
        "character": "よく落ちてるんだ",
        "definition": "You often find them here.",
        "timestamp": "0:04:17",
        "audio": "/audio/15/0.04.17.mp3"
    },
    "43": {
        "speaker": "SASAKO",
        "character": "遮光器土偶ですね",
        "definition": "It's a spaceman clay figure.",
        "timestamp": "0:04:20",
        "audio": "/audio/15/0.04.20.mp3"
    },
    "44": {
        "speaker": "POLAR BEAR",
        "character": "うん",
        "definition": "Yes.",
        "timestamp": "0:04:22",
        "audio": "/audio/15/0.04.22.mp3"
    },
    "45": {
        "speaker": "PANDA",
        "character": "面白い顔だね",
        "definition": "What a weird face.",
        "timestamp": "0:04:23",
        "audio": "/audio/15/0.04.23.mp3"
    },
    "46": {
        "speaker": "PENGUIN",
        "character": "僕だけかな　雑草取り真面目にやってるの",
        "definition": "Am I the only one that's taking this seriously?",
        "timestamp": "0:04:27",
        "audio": "/audio/15/0.04.27.mp3"
    },
    "47": {
        "speaker": "SLOTH",
        "character": "僕も～",
        "definition": "I am...",
        "timestamp": "0:04:32",
        "audio": "/audio/15/0.04.32.mp3"
    },
    "48": {
        "speaker": "SLOTH",
        "character": "いるよ～～",
        "definition": "here too...",
        "timestamp": "0:04:34",
        "audio": "/audio/15/0.04.34.mp3"
    },
    "49": {
        "speaker": "PENGUIN",
        "character": "怠け者くん",
        "definition": "Sloth! I'll... do... my... best...",
        "timestamp": "0:04:38",
        "audio": "/audio/15/0.04.38.mp3"
    },
    "50": {
        "speaker": "PENGUIN",
        "character": "やる気はあるんだけどな",
        "definition": "At least you're determined.",
        "timestamp": "0:04:52",
        "audio": "/audio/15/0.04.52.mp3"
    },
    "51": {
        "speaker": "PANDA",
        "character": "クーラーは涼しいな",
        "definition": "The air conditioning is so cool.",
        "timestamp": "0:05:00",
        "audio": "/audio/15/0.05.00.mp3"
    },
    "52": {
        "speaker": "PANDA",
        "character": "ねぇ　笹持ってきて　お母さん",
        "definition": "Hey, Mom, could you bring me some bamboo grass?",
        "timestamp": "0:05:03",
        "audio": "/audio/15/0.05.03.mp3"
    },
    "53": {
        "speaker": "PENGUIN",
        "character": "涼しいでしょう",
        "definition": "It's nice and cool, isn't it?",
        "timestamp": "0:05:09",
        "audio": "/audio/15/0.05.09.mp3"
    },
    "54": {
        "speaker": "PANDA",
        "character": "あ　ペンギンさん何してるの",
        "definition": "Oh, Mr. Penguin, what are you doing here?",
        "timestamp": "0:05:12",
        "audio": "/audio/15/0.05.12.mp3"
    },
    "55": {
        "speaker": "PENGUIN",
        "character": "何してるのじゃないよパンダ君　雑草取りは？",
        "definition": "What do you mean what am I doing here?! What happened to weeding?!",
        "timestamp": "0:05:15",
        "audio": "/audio/15/0.05.15.mp3"
    },
    "56": {
        "speaker": "PANDA",
        "character": "ペンギンさんはなんでそんなに雑草取りがすきなの",
        "definition": "Why do you like weeding so much, Mr. Penguin?",
        "timestamp": "0:05:19",
        "audio": "/audio/15/0.05.19.mp3"
    },
    "57": {
        "speaker": "PENGUIN",
        "character": "好きじゃないよ",
        "definition": "I don't like it!",
        "timestamp": "0:05:25",
        "audio": "/audio/15/0.05.25.mp3"
    },
    "58": {
        "speaker": "PENGUIN",
        "character": "けど　このままじゃ一日じゃ終わらないよ",
        "definition": "But at this rate, we won't finish today!",
        "timestamp": "0:05:27",
        "audio": "/audio/15/0.05.27.mp3"
    },
    "59": {
        "speaker": "PANDA",
        "character": "分かったよ",
        "definition": "All right. Jeez.",
        "timestamp": "0:05:33",
        "audio": "/audio/15/0.05.33.mp3"
    },
    "60": {
        "speaker": "PENGUIN",
        "character": "じゃ　行こうか",
        "definition": "Then, let's go.",
        "timestamp": "0:05:36",
        "audio": "/audio/15/0.05.36.mp3"
    },
    "61": {
        "speaker": "PANDA",
        "character": "うん　昼寝してからすぐ行くよ",
        "definition": "Okay. I'll be there right after my nap. Don't suck me up!",
        "timestamp": "0:05:37",
        "audio": "/audio/15/0.05.37.mp3"
    },
    "62": {
        "speaker": "PANDA",
        "character": "暑いな",
        "definition": "It's so hot.",
        "timestamp": "0:05:51",
        "audio": "/audio/15/0.05.51.mp3"
    },
    "63": {
        "speaker": "PENGUIN",
        "character": "僕だって暑いよ",
        "definition": "It's hot for me, too.",
        "timestamp": "0:05:53",
        "audio": "/audio/15/0.05.53.mp3"
    },
    "64": {
        "speaker": "PENGUIN",
        "character": "何！　え！　火事？",
        "definition": "What's that? A fire?",
        "timestamp": "0:05:58",
        "audio": "/audio/15/0.05.58.mp3"
    },
    "65": {
        "speaker": "PANDA",
        "character": "ええ？",
        "definition": "What?",
        "timestamp": "0:06:00",
        "audio": "/audio/15/0.06.00.mp3"
    },
    "66": {
        "speaker": "PENGUIN",
        "character": "パンダ君　急ごう",
        "definition": "Let's hurry, Panda! Okay.",
        "timestamp": "0:06:01",
        "audio": "/audio/15/0.06.01.mp3"
    },
    "67": {
        "speaker": "PENGUIN",
        "character": "ちょっと　何してるの",
        "definition": "Hey, now. What are you doing?",
        "timestamp": "0:06:08",
        "audio": "/audio/15/0.06.08.mp3"
    },
    "68": {
        "speaker": "POLAR BEAR",
        "character": "バーベキュー",
        "definition": "Barbecuing.",
        "timestamp": "0:06:12",
        "audio": "/audio/15/0.06.12.mp3"
    },
    "69": {
        "speaker": "PENGUIN",
        "character": "らまさん　お腹いっぱいだって言ってたでしょう",
        "definition": "Didn't you say you were full, Mr. Llama?!",
        "timestamp": "0:06:13",
        "audio": "/audio/15/0.06.13.mp3"
    },
    "70": {
        "speaker": "LLAMA",
        "character": "バーベキューは別腹ですよ",
        "definition": "Barbecue goes into a separate stomach.",
        "timestamp": "0:06:17",
        "audio": "/audio/15/0.06.17.mp3"
    },
    "71": {
        "speaker": "PENGUIN",
        "character": "聞いたことないよ　そんな言葉",
        "definition": "I've never heard anything like that!",
        "timestamp": "0:06:19",
        "audio": "/audio/15/0.06.19.mp3"
    },
    "72": {
        "speaker": "SASAKO",
        "character": "ペンギンさん　そこで拾った土偶です",
        "definition": "Mr. Penguin, I found this clay figure over there.",
        "timestamp": "0:06:22",
        "audio": "/audio/15/0.06.22.mp3"
    },
    "73": {
        "speaker": "PENGUIN",
        "character": "また？",
        "definition": "Again?",
        "timestamp": "0:06:27",
        "audio": "/audio/15/0.06.27.mp3"
    },
    "74": {
        "speaker": "PENGUIN",
        "character": "だから　すごいんだけれど　要らないよ　その報告は",
        "definition": "That's amazing and all, but we didn't need to know that.",
        "timestamp": "0:06:28",
        "audio": "/audio/15/0.06.28.mp3"
    },
    "75": {
        "speaker": "PANDA",
        "character": "見せて　見せて",
        "definition": "Let me see! Let me see!",
        "timestamp": "0:06:38",
        "audio": "/audio/15/0.06.38.mp3"
    },
    "76": {
        "speaker": "POLAR BEAR",
        "character": "らまさん",
        "definition": "It's ready, Mr. Llama.",
        "timestamp": "0:06:39",
        "audio": "/audio/15/0.06.39.mp3"
    },
    "77": {
        "speaker": "SASAKO",
        "character": "焼けたよ",
        "definition": "Here you go.",
        "timestamp": "0:06:40",
        "audio": "/audio/15/0.06.40.mp3"
    },
    "78": {
        "speaker": "LLAMA",
        "character": "ありがとうございます",
        "definition": "Thank you very much.",
        "timestamp": "0:06:41",
        "audio": "/audio/15/0.06.41.mp3"
    },
    "79": {
        "speaker": "PENGUIN",
        "character": "僕ちょっと倒れるよ",
        "definition": "I'm going to collapse now.",
        "timestamp": "0:06:43",
        "audio": "/audio/15/0.06.43.mp3"
    },
    "80": {
        "speaker": "SASAKO",
        "character": "ペンギンさん",
        "definition": "Mr. Penguin?!",
        "timestamp": "0:06:48",
        "audio": "/audio/15/0.06.48.mp3"
    },
    "81": {
        "speaker": "POLAR BEAR",
        "character": "ナイス　ショット",
        "definition": "Nice shot!",
        "timestamp": "0:06:56",
        "audio": "/audio/15/0.06.56.mp3"
    },
    "82": {
        "speaker": "LLAMA",
        "character": "打てるもんですね",
        "definition": "It's not that hard at all.",
        "timestamp": "0:07:00",
        "audio": "/audio/15/0.07.00.mp3"
    },
    "83": {
        "speaker": "PENGUIN",
        "character": "何してるの",
        "definition": "What are you doing?!",
        "timestamp": "0:07:02",
        "audio": "/audio/15/0.07.02.mp3"
    },
    "84": {
        "speaker": "POLAR BEAR",
        "character": "ゴルフ",
        "definition": "Golfing.",
        "timestamp": "0:07:04",
        "audio": "/audio/15/0.07.04.mp3"
    },
    "85": {
        "speaker": "PENGUIN",
        "character": "誰も僕を見習って頑張ろうとしないなんて",
        "definition": "No one is following my exampleof working hard.",
        "timestamp": "0:07:06",
        "audio": "/audio/15/0.07.06.mp3"
    },
    "86": {
        "speaker": "POLAR BEAR",
        "character": "ごめん",
        "definition": "Sorry.",
        "timestamp": "0:07:11",
        "audio": "/audio/15/0.07.11.mp3"
    },
    "87": {
        "speaker": "SASAKO",
        "character": "ペンギンさん",
        "definition": "Mr. Penguin.",
        "timestamp": "0:07:13",
        "audio": "/audio/15/0.07.13.mp3"
    },
    "88": {
        "speaker": "PENGUIN",
        "character": "何　笹子さん　また土偶？",
        "definition": "What is it, Miss Sasako? Another clay figure?",
        "timestamp": "0:07:14",
        "audio": "/audio/15/0.07.14.mp3"
    },
    "89": {
        "speaker": "SASAKO",
        "character": "いいえ　皆でここだけはやったんですよ",
        "definition": "No. We actually all got this section done.",
        "timestamp": "0:07:17",
        "audio": "/audio/15/0.07.17.mp3"
    },
    "90": {
        "speaker": "PENGUIN",
        "character": "え？",
        "definition": "Huh? Oh.",
        "timestamp": "0:07:21",
        "audio": "/audio/15/0.07.21.mp3"
    },
    "91": {
        "speaker": "PANDA",
        "character": "この木陰なら涼しいし",
        "definition": "Mr. Llama said it would be cooler in the shade and you'd be able to rest here.",
        "timestamp": "0:07:25",
        "audio": "/audio/15/0.07.25.mp3"
    },
    "92": {
        "speaker": "LLAMA",
        "character": "テラスが日が射してきちゃって",
        "definition": "The sun was pretty strong on the terrace.",
        "timestamp": "0:07:31",
        "audio": "/audio/15/0.07.31.mp3"
    },
    "93": {
        "speaker": "POLAR BEAR",
        "character": "ごめんねm( __ __ )m",
        "definition": "Sorry about that.",
        "timestamp": "0:07:36",
        "audio": "/audio/15/0.07.36.mp3"
    },
    "94": {
        "speaker": "POLAR BEAR",
        "character": "友達と一緒に賑やかにできたほうがいいなぁって",
        "definition": "I thought it'd be a lot more fun if we did this all together.",
        "timestamp": "0:07:39",
        "audio": "/audio/15/0.07.39.mp3"
    },
    "95": {
        "speaker": "POLAR BEAR",
        "character": "だって　みんなでこうしてるだけで　楽しいよ",
        "definition": "Because... it's fun just having everyone together.",
        "timestamp": "0:07:44",
        "audio": "/audio/15/0.07.44.mp3"
    },
    "96": {
        "speaker": "PENGUIN",
        "character": "そうだね",
        "definition": "You're right.",
        "timestamp": "0:08:01",
        "audio": "/audio/15/0.08.01.mp3"
    },
    "97": {
        "speaker": "PENGUIN",
        "character": "僕大事なこと忘れてたみたい",
        "definition": "It seems I forgot something rather important.",
        "timestamp": "0:08:02",
        "audio": "/audio/15/0.08.02.mp3"
    },
    "98": {
        "speaker": "POLAR BEAR",
        "character": "ミントティー　飲む？",
        "definition": "Would you like some mint tea?",
        "timestamp": "0:08:05",
        "audio": "/audio/15/0.08.05.mp3"
    },
    "99": {
        "speaker": "PENGUIN",
        "character": "うん",
        "definition": "Please.",
        "timestamp": "0:08:08",
        "audio": "/audio/15/0.08.08.mp3"
    },
    "100": {
        "speaker": "SASAKO",
        "character": "私たちは　雑草取りに戻りましょうか",
        "definition": "The rest of us should get back to weeding.",
        "timestamp": "0:08:10",
        "audio": "/audio/15/0.08.10.mp3"
    },
    "101": {
        "speaker": "PANDA",
        "character": "うん",
        "definition": "Okay.",
        "timestamp": "0:08:14",
        "audio": "/audio/15/0.08.14.mp3"
    },
    "102": {
        "speaker": "SASAKO",
        "character": "ペンギンさんは休んでてください",
        "definition": "Please take it easy, Mr. Penguin.",
        "timestamp": "0:08:15",
        "audio": "/audio/15/0.08.15.mp3"
    },
    "103": {
        "speaker": "SASAKO",
        "character": "じゃあ",
        "definition": "Well, then.",
        "timestamp": "0:08:18",
        "audio": "/audio/15/0.08.18.mp3"
    },
    "104": {
        "speaker": "LLAMA",
        "character": "もう一頑張りしますか",
        "definition": "Let's give it another go. I can't eat anymore... It's your turn, Mr. Penguin.",
        "timestamp": "0:08:19",
        "audio": "/audio/15/0.08.19.mp3"
    },
    "105": {
        "speaker": "SLOTH",
        "character": "大～丈～夫～",
        "definition": "It's... all... good...",
        "timestamp": "0:08:34",
        "audio": "/audio/15/0.08.34.mp3"
    },
    "106": {
        "speaker": "SLOTH",
        "character": "後は　僕が～",
        "definition": "I'll... do the...",
        "timestamp": "0:08:37",
        "audio": "/audio/15/0.08.37.mp3"
    },
    "107": {
        "speaker": "PANDA",
        "character": "終わらないね",
        "definition": "This isn't ending.",
        "timestamp": "0:08:46",
        "audio": "/audio/15/0.08.46.mp3"
    },
    "108": {
        "speaker": "SASAKO",
        "character": "どうしましょうか",
        "definition": "What should we do?",
        "timestamp": "0:08:48",
        "audio": "/audio/15/0.08.48.mp3"
    },
    "109": {
        "speaker": "LLAMA",
        "character": "バービキュ食べ過ぎて　僕もう草は食べられません",
        "definition": "I ate too much barbecue and can't eat any more weeds.",
        "timestamp": "0:08:50",
        "audio": "/audio/15/0.08.50.mp3"
    },
    "110": {
        "speaker": "POLAR BEAR",
        "character": "もしもし",
        "definition": "Hello?",
        "timestamp": "0:09:03",
        "audio": "/audio/15/0.09.03.mp3"
    },
    "111": {
        "speaker": "GRIZZLY",
        "character": "何だよ　このクソ暑い中に呼び出しやがって",
        "definition": "What the hell do you want, calling me over in this damn heat?",
        "timestamp": "0:09:06",
        "audio": "/audio/15/0.09.06.mp3"
    },
    "112": {
        "speaker": "POLAR BEAR",
        "character": "庭の雑草が伸びちゃってさ",
        "definition": "The yard was getting overgrown with weeds.",
        "timestamp": "0:09:10",
        "audio": "/audio/15/0.09.10.mp3"
    },
    "113": {
        "speaker": "GRIZZLY",
        "character": "庭の雑草？　白熊",
        "definition": "The weeds in the yard? You aren't thinking about asking me to pull the weeds, are you, Polar Bear?!",
        "timestamp": "0:09:13",
        "audio": "/audio/15/0.09.13.mp3"
    },
    "114": {
        "speaker": "POLAR BEAR",
        "character": "いい？",
        "definition": "Could you?",
        "timestamp": "0:09:22",
        "audio": "/audio/15/0.09.22.mp3"
    },
    "115": {
        "speaker": "GRIZZLY",
        "character": "いい？",
        "definition": "Could I?",
        "timestamp": "0:09:23",
        "audio": "/audio/15/0.09.23.mp3"
    },
    "116": {
        "speaker": "GRIZZLY",
        "character": "じゃねぇー",
        "definition": "What do you mean, could I?!",
        "timestamp": "0:09:24",
        "audio": "/audio/15/0.09.24.mp3"
    },
    "117": {
        "speaker": "GRIZZLY",
        "character": "これでいいのか",
        "definition": "Is that good enough?!",
        "timestamp": "0:09:38",
        "audio": "/audio/15/0.09.38.mp3"
    },
    "118": {
        "speaker": "PENGUIN",
        "character": "なんて　暴力的で　なんて　丁寧な仕事だ",
        "definition": "Such violent, yet such careful work.",
        "timestamp": "0:09:43",
        "audio": "/audio/15/0.09.43.mp3"
    },
    "119": {
        "speaker": "GRIZZLY",
        "character": "飯食わせろ！",
        "definition": "Give me food!",
        "timestamp": "0:09:47",
        "audio": "/audio/15/0.09.47.mp3"
    },
    "120": {
        "speaker": "POLAR BEAR",
        "character": "はい",
        "definition": "Here. It's great!",
        "timestamp": "0:09:50",
        "audio": "/audio/15/0.09.50.mp3"
    },
    "121": {
        "speaker": "GRIZZLY",
        "character": "またな",
        "definition": "See ya later!",
        "timestamp": "0:09:56",
        "audio": "/audio/15/0.09.56.mp3"
    },
    "122": {
        "speaker": "PENGUIN",
        "character": "暴風のように去っていた",
        "definition": "And then he left like a storm.",
        "timestamp": "0:09:59",
        "audio": "/audio/15/0.09.59.mp3"
    },
    "123": {
        "speaker": "POLAR BEAR",
        "character": "今日はおごるよ",
        "definition": "I'll treat you today. Huh?",
        "timestamp": "0:10:03",
        "audio": "/audio/15/0.10.03.mp3"
    },
    "124": {
        "speaker": "POLAR BEAR",
        "character": "ぺんぎんさんにも迷惑かけちゃったし",
        "definition": "I've caused you a lot of trouble, Mr. Penguin.",
        "timestamp": "0:10:06",
        "audio": "/audio/15/0.10.06.mp3"
    },
    "125": {
        "speaker": "POLAR BEAR",
        "character": "飲もうか",
        "definition": "Let's have a drink.",
        "timestamp": "0:10:09",
        "audio": "/audio/15/0.10.09.mp3"
    },
    "126": {
        "speaker": "PENGUIN",
        "character": "うん(/ω＼)",
        "definition": "Okay!",
        "timestamp": "0:10:13",
        "audio": "/audio/15/0.10.13.mp3"
    },
    "127": {
        "speaker": "KOALA",
        "character": "やぁ　今日は働いたね",
        "definition": "We worked so hard today!",
        "timestamp": "0:10:15",
        "audio": "/audio/15/0.10.15.mp3"
    },
    "128": {
        "speaker": "SASAKO",
        "character": "白熊さんもこっちに来て飲みましょう",
        "definition": "You should come over here and have a drink, too, Mr. Polar Bear.",
        "timestamp": "0:10:18",
        "audio": "/audio/15/0.10.18.mp3"
    },
    "129": {
        "speaker": "PENGUIN",
        "character": "楽しにゃ",
        "definition": "This is fun!",
        "timestamp": "0:10:25",
        "audio": "/audio/15/0.10.25.mp3"
    },
    "130": {
        "speaker": "POLAR BEAR",
        "character": "でしょう",
        "definition": "Isn't it?",
        "timestamp": "0:10:29",
        "audio": "/audio/15/0.10.29.mp3"
    },
    "131": {
        "speaker": "PENGUIN",
        "character": "白熊君相談って何",
        "definition": "What did you want to talk about, Polar Bear?",
        "timestamp": "0:10:42",
        "audio": "/audio/15/0.10.42.mp3"
    },
    "132": {
        "speaker": "SASAKO",
        "character": "それが",
        "definition": "Well...",
        "timestamp": "0:10:47",
        "audio": "/audio/15/0.10.47.mp3"
    },
    "133": {
        "speaker": "PENGUIN",
        "character": "どうしたの　僕でよかったら相談に乗るよ",
        "definition": "What's the matter? I'll be happy to listen.",
        "timestamp": "0:10:54",
        "audio": "/audio/15/0.10.54.mp3"
    },
    "134": {
        "speaker": "PENGUIN",
        "character": "え工ｴｴｪｪ(´д｀)ｪｪｴｴ工",
        "definition": "What?!",
        "timestamp": "0:10:58",
        "audio": "/audio/15/0.10.58.mp3"
    },
    "135": {
        "speaker": "PENGUIN",
        "character": "たった数日でこんなに伸びたの",
        "definition": "It's only been a few days and they grew this much?!",
        "timestamp": "0:10:59",
        "audio": "/audio/15/0.10.59.mp3"
    },
    "136": {
        "speaker": "POLAR BEAR",
        "character": "夏の雑草は　伸びるの早いんだよ",
        "definition": "The weeds grow fast in the summer.",
        "timestamp": "0:11:03",
        "audio": "/audio/15/0.11.03.mp3"
    },
    "137": {
        "speaker": "PENGUIN",
        "character": "僕が手伝う理由が見えないんだけど",
        "definition": "I'm not seeing why I should help here.",
        "timestamp": "0:11:07",
        "audio": "/audio/15/0.11.07.mp3"
    },
    "138": {
        "speaker": "POLAR BEAR",
        "character": "ほら　僕は寒いところの生き物だから",
        "definition": "You know, because I'm an animal that's from a cold place.",
        "timestamp": "0:11:10",
        "audio": "/audio/15/0.11.10.mp3"
    },
    "139": {
        "speaker": "PENGUIN",
        "character": "だから　僕もだよ",
        "definition": "I'm telling you, so am I! This is a clay figure I just found.",
        "timestamp": "0:11:14",
        "audio": "/audio/15/0.11.14.mp3"
    },
    "140": {
        "speaker": "PENGUIN",
        "character": "笹子さん　その報告はもういいから",
        "definition": "Miss Sasako, we really don't need to hear that anymore.",
        "timestamp": "0:11:20",
        "audio": "/audio/15/0.11.20.mp3"
    },
    "141": {
        "speaker": "SASAKO",
        "character": "夏ですね",
        "definition": "It's totally summer. It is summer.",
        "timestamp": "0:11:34",
        "audio": "/audio/15/0.11.34.mp3"
    },
    "142": {
        "speaker": "SASAKO",
        "character": "今年は蝉がよく泣きますね",
        "definition": "You can hear the cicadas quite well this year.",
        "timestamp": "0:11:37",
        "audio": "/audio/15/0.11.37.mp3"
    },
    "143": {
        "speaker": "POLAR BEAR",
        "character": "雄は腹腔内の発音筋と発音膜で音を出して共鳴室で音を大きく出して雌を呼んでるね",
        "definition": "The males use their internal sound-producing organ and sound-producing membrane to produce the sound, then use their resonance chamber to amplify the sound to call upon the females.",
        "timestamp": "0:11:40",
        "audio": "/audio/15/0.11.40.mp3"
    },
    "144": {
        "speaker": "SASAKO",
        "character": "情緒のない言い方やめてくれますか",
        "definition": "Could you stop saying things with so little emotion?",
        "timestamp": "0:11:50",
        "audio": "/audio/15/0.11.50.mp3"
    },
    "145": {
        "speaker": "PENGUIN",
        "character": "どうしたのパンダ君",
        "definition": "What's wrong, Panda?",
        "timestamp": "0:11:57",
        "audio": "/audio/15/0.11.57.mp3"
    },
    "146": {
        "speaker": "PENGUIN",
        "character": "食べないの　パンダあんぱん",
        "definition": "Don't you want a panda red bean bun?",
        "timestamp": "0:11:59",
        "audio": "/audio/15/0.11.59.mp3"
    },
    "147": {
        "speaker": "PENGUIN",
        "character": "体調悪いの",
        "definition": "Are you not feeling well?",
        "timestamp": "0:12:01",
        "audio": "/audio/15/0.12.01.mp3"
    },
    "148": {
        "speaker": "PANDA",
        "character": "毎日パンじゃなくて　たまには高級フルーツでも買ってきてよ",
        "definition": "Instead of bread everyday, could you buy some fancy fruits once in a while?",
        "timestamp": "0:12:03",
        "audio": "/audio/15/0.12.03.mp3"
    },
    "149": {
        "speaker": "PENGUIN",
        "character": "果物屋にはペン子さんがいないじゃない",
        "definition": "But Miss Penko isn't at the fruit shop.",
        "timestamp": "0:12:09",
        "audio": "/audio/15/0.12.09.mp3"
    },
    "150": {
        "speaker": "SASAKO",
        "character": "ペンギンさん",
        "definition": "Mr. Penguin.",
        "timestamp": "0:12:12",
        "audio": "/audio/15/0.12.12.mp3"
    },
    "151": {
        "speaker": "PENGUIN",
        "character": "何？　パン食べる",
        "definition": "What is it? Do you want some bread?",
        "timestamp": "0:12:13",
        "audio": "/audio/15/0.12.13.mp3"
    },
    "152": {
        "speaker": "SASAKO",
        "character": "いいえ　そうじゃなくて",
        "definition": "No, it's not that.",
        "timestamp": "0:12:16",
        "audio": "/audio/15/0.12.16.mp3"
    },
    "153": {
        "speaker": "SASAKO",
        "character": "ペンギンさん　夏にはペン子さんに告白してドライブって言ってませんでしたっけ",
        "definition": "Didn't you say that, come summer,you'd confess your love to Miss Penko, and take her for a drive?",
        "timestamp": "0:12:19",
        "audio": "/audio/15/0.12.19.mp3"
    },
    "154": {
        "speaker": "POLAR BEAR",
        "character": "もう夏だね",
        "definition": "It's already summer.",
        "timestamp": "0:12:27",
        "audio": "/audio/15/0.12.27.mp3"
    },
    "155": {
        "speaker": "PENGUIN",
        "character": "夏とは言ったけど今年のとはいってないでしょう",
        "definition": "I know I said summer, but I didn't say it would be this summer.",
        "timestamp": "0:12:32",
        "audio": "/audio/15/0.12.32.mp3"
    },
    "156": {
        "speaker": "PENGUIN",
        "character": "来年かもしれないし　再来年かもしれないし　十年後の夏かもしれないよ",
        "definition": "It could be next year, or even the year after that. Or even ten years from now.",
        "timestamp": "0:12:36",
        "audio": "/audio/15/0.12.36.mp3"
    },
    "157": {
        "speaker": "SASAKO",
        "character": "そんな長いスパンの話なんですか",
        "definition": "Was this really supposed to take that much time?",
        "timestamp": "0:12:43",
        "audio": "/audio/15/0.12.43.mp3"
    },
    "158": {
        "speaker": "PANDA",
        "character": "もう　今からチョロっと告白してきなよ",
        "definition": "Why don't you just go ask her out real quick—",
        "timestamp": "0:12:46",
        "audio": "/audio/15/0.12.46.mp3"
    },
    "159": {
        "speaker": "PENGUIN",
        "character": "チョロっとって　ちょっと待ってよ",
        "definition": "What do you mean, real quick?! Wait a minute! I think it's a good idea. Why don't you go ask her out? What?! Well, I have to prepare my heart if I'm going to confess.",
        "timestamp": "0:12:49",
        "audio": "/audio/15/0.12.49.mp3"
    },
    "160": {
        "speaker": "PENGUIN",
        "character": "いやいや　その前に心の準備の用意の前振りをだね",
        "definition": "Er, um... and before that, I have to get ready to start to prepare my heart.",
        "timestamp": "0:13:03",
        "audio": "/audio/15/0.13.03.mp3"
    },
    "161": {
        "speaker": "SASAKO",
        "character": "でも早く告白しないと　ペン子さん取られちゃうかもしれないですよ",
        "definition": "But if you don't hurry and confess, someone might beat you to it.",
        "timestamp": "0:13:08",
        "audio": "/audio/15/0.13.08.mp3"
    },
    "162": {
        "speaker": "PENGUIN",
        "character": "けど　ふられたらどうしよう",
        "definition": "But what if I get rejected?",
        "timestamp": "0:13:15",
        "audio": "/audio/15/0.13.15.mp3"
    },
    "163": {
        "speaker": "POLAR BEAR",
        "character": "大丈夫だよ　まだふられたわけじゃないんだから",
        "definition": "It'll be okay. You haven't been rejected yet.",
        "timestamp": "0:13:19",
        "audio": "/audio/15/0.13.19.mp3"
    },
    "164": {
        "speaker": "SASAKO",
        "character": "そうですよ",
        "definition": "He's right!",
        "timestamp": "0:13:23",
        "audio": "/audio/15/0.13.23.mp3"
    },
    "165": {
        "speaker": "POLAR BEAR",
        "character": "ちゃんと告白して　ふられようよ",
        "definition": "First ask her out, and then get rejected.",
        "timestamp": "0:13:25",
        "audio": "/audio/15/0.13.25.mp3"
    },
    "166": {
        "speaker": "SASAKO",
        "character": "白熊さん",
        "definition": "Mr. Polar Bear!",
        "timestamp": "0:13:28",
        "audio": "/audio/15/0.13.28.mp3"
    },
    "167": {
        "speaker": "PENGUIN",
        "character": "そうだね",
        "definition": "You're right.",
        "timestamp": "0:13:30",
        "audio": "/audio/15/0.13.30.mp3"
    },
    "168": {
        "speaker": "PENGUIN",
        "character": "いつかの夏にと思ってたけど",
        "definition": "I was thinking of some future summer,",
        "timestamp": "0:13:33",
        "audio": "/audio/15/0.13.33.mp3"
    },
    "169": {
        "speaker": "PENGUIN",
        "character": "もう告白してしまおうかな",
        "definition": "but maybe I'll just ask her out.",
        "timestamp": "0:13:37",
        "audio": "/audio/15/0.13.37.mp3"
    },
    "170": {
        "speaker": "SASAKO",
        "character": "そうですよ",
        "definition": "That's the spirit!",
        "timestamp": "0:13:40",
        "audio": "/audio/15/0.13.40.mp3"
    },
    "171": {
        "speaker": "PANDA",
        "character": "そうだよ　ふられるなら　早いほうがいいよ",
        "definition": "Yeah! If you're going to be rejected, you should get it over with.",
        "timestamp": "0:13:42",
        "audio": "/audio/15/0.13.42.mp3"
    },
    "172": {
        "speaker": "SASAKO",
        "character": "パンダ君",
        "definition": "Panda!",
        "timestamp": "0:13:46",
        "audio": "/audio/15/0.13.46.mp3"
    },
    "173": {
        "speaker": "PENGUIN",
        "character": "よし　行くよ",
        "definition": "All right! I'm going to do it!",
        "timestamp": "0:13:48",
        "audio": "/audio/15/0.13.48.mp3"
    },
    "174": {
        "speaker": "PENGUIN",
        "character": "これで　ようやく彼女の名前も分かるしね",
        "definition": "And then I'll finally know her name for sure. What?",
        "timestamp": "0:13:50",
        "audio": "/audio/15/0.13.50.mp3"
    },
    "175": {
        "speaker": "PENGUIN",
        "character": "何？",
        "definition": "What?",
        "timestamp": "0:13:55",
        "audio": "/audio/15/0.13.55.mp3"
    },
    "176": {
        "speaker": "PANDA",
        "character": "ペン子さんじゃないの",
        "definition": "It's not Miss Penko?",
        "timestamp": "0:13:56",
        "audio": "/audio/15/0.13.56.mp3"
    },
    "177": {
        "speaker": "PENGUIN",
        "character": "え？言ってなかった",
        "definition": "Huh? Didn't I tell you? \"Miss Penko\" is the name I gave her. You don't mean... that you don't know her name?",
        "timestamp": "0:13:57",
        "audio": "/audio/15/0.13.57.mp3"
    },
    "178": {
        "speaker": "PENGUIN",
        "character": "知らないよ",
        "definition": "I have no idea.",
        "timestamp": "0:14:08",
        "audio": "/audio/15/0.14.08.mp3"
    },
    "179": {
        "speaker": "PENGUIN",
        "character": "悪い？",
        "definition": "Is that bad?",
        "timestamp": "0:14:09",
        "audio": "/audio/15/0.14.09.mp3"
    },
    "180": {
        "speaker": "SASAKO",
        "character": "だって",
        "definition": "But...",
        "timestamp": "0:14:10",
        "audio": "/audio/15/0.14.10.mp3"
    },
    "181": {
        "speaker": "PENGUIN",
        "character": "じゃ　笹子さんは名前も知らない花をきれいだなって思ったことはないですか",
        "definition": "Then tell me, Miss Sasako, haven't you ever thought that a flower you didn't know the name of was pretty?",
        "timestamp": "0:14:11",
        "audio": "/audio/15/0.14.11.mp3"
    },
    "182": {
        "speaker": "PENGUIN",
        "character": "名前も知らない美味しい魚を食べたことはないですか",
        "definition": "Haven't you ever eaten a delicious fish that you didn't know the name of?",
        "timestamp": "0:14:16",
        "audio": "/audio/15/0.14.16.mp3"
    },
    "183": {
        "speaker": "PENGUIN",
        "character": "名前も知らない曲に心揺さぶれたことはないですか",
        "definition": "Haven't you ever been moved by a song you didn't know the name of?",
        "timestamp": "0:14:20",
        "audio": "/audio/15/0.14.20.mp3"
    },
    "184": {
        "speaker": "PENGUIN",
        "character": "名前も知らない未知の風景に美しいと思ったことはないですか",
        "definition": "Haven't you ever thought the scenery",
        "timestamp": "0:14:23",
        "audio": "/audio/15/0.14.23.mp3"
    },
    "185": {
        "speaker": "SASAKO",
        "character": "分かりましたから　もう行ってください",
        "definition": "I get it, so please, just go. of an unknown place was beautiful?",
        "timestamp": "0:14:24",
        "audio": "/audio/15/0.14.24.mp3"
    },
    "186": {
        "speaker": "PENGUIN",
        "character": "じゃ",
        "definition": "Bye!",
        "timestamp": "0:14:27",
        "audio": "/audio/15/0.14.27.mp3"
    },
    "187": {
        "speaker": "SASAKO",
        "character": "名前も知らないんですね",
        "definition": "He doesn't even know her name.",
        "timestamp": "0:14:32",
        "audio": "/audio/15/0.14.32.mp3"
    },
    "188": {
        "speaker": "SASAKO",
        "character": "大丈夫ですかね",
        "definition": "I wonder if he'll be okay.",
        "timestamp": "0:14:35",
        "audio": "/audio/15/0.14.35.mp3"
    },
    "189": {
        "speaker": "PENKO",
        "character": "ありがとうございました",
        "definition": "Thank you very much.",
        "timestamp": "0:14:41",
        "audio": "/audio/15/0.14.41.mp3"
    },
    "190": {
        "speaker": "PENKO",
        "character": "いらっしゃいませ",
        "definition": "Welcome! U-Um...",
        "timestamp": "0:14:43",
        "audio": "/audio/15/0.14.43.mp3"
    },
    "191": {
        "speaker": "PENGUIN",
        "character": "今日はサービス券もらいに来たんじゃないです",
        "definition": "I didn't come today to get  service coupons!",
        "timestamp": "0:14:47",
        "audio": "/audio/15/0.14.47.mp3"
    },
    "192": {
        "speaker": "PENGUIN",
        "character": "言わなくていい言葉だった",
        "definition": "I didn't have to mention that...",
        "timestamp": "0:14:53",
        "audio": "/audio/15/0.14.53.mp3"
    },
    "193": {
        "speaker": "PENGUIN",
        "character": "待とう　人がいなくなるのを",
        "definition": "I'm going to wait... until everyone leaves.",
        "timestamp": "0:15:00",
        "audio": "/audio/15/0.15.00.mp3"
    },
    "194": {
        "speaker": "LADY",
        "character": "またくるわ",
        "definition": "I'll come again.",
        "timestamp": "0:15:05",
        "audio": "/audio/15/0.15.05.mp3"
    },
    "195": {
        "speaker": "PENKO",
        "character": "ありがとうございました",
        "definition": "Thank you very much.",
        "timestamp": "0:15:07",
        "audio": "/audio/15/0.15.07.mp3"
    },
    "196": {
        "speaker": "PENGUIN",
        "character": "いまだ　今しかない　でも緊張してきた",
        "definition": "Now's my chance. Now's my only chance. But I'm getting nervous.",
        "timestamp": "0:15:12",
        "audio": "/audio/15/0.15.12.mp3"
    },
    "197": {
        "speaker": "PENGUIN",
        "character": "こういう時どうするんだっけ",
        "definition": "What am I supposed to do at times like these?",
        "timestamp": "0:15:17",
        "audio": "/audio/15/0.15.17.mp3"
    },
    "198": {
        "speaker": "PENGUIN",
        "character": "人という字3回書いて呑むんだ",
        "definition": "I write \"person\" on my hand and swallow it.",
        "timestamp": "0:15:20",
        "audio": "/audio/15/0.15.20.mp3"
    },
    "199": {
        "speaker": "PENGUIN",
        "character": "いや　待ってよ",
        "definition": "Or, wait... Since I'm a penguin, am I supposed to write \"penguin\" three times and swallow it?",
        "timestamp": "0:15:24",
        "audio": "/audio/15/0.15.24.mp3"
    },
    "200": {
        "speaker": "PENGUIN",
        "character": "ペ－ン－ギ－ン",
        "definition": "Pe-n-gui-n, pe-n-gui-n, pe-n-gui-n.",
        "timestamp": "0:15:31",
        "audio": "/audio/15/0.15.31.mp3"
    },
    "201": {
        "speaker": "PENGUIN",
        "character": "そんなたくさんの文字呑めるか",
        "definition": "How the heck am I supposed to swallow that many letters?!",
        "timestamp": "0:15:36",
        "audio": "/audio/15/0.15.36.mp3"
    },
    "202": {
        "speaker": "PENKO",
        "character": "あのう",
        "definition": "Um...",
        "timestamp": "0:15:39",
        "audio": "/audio/15/0.15.39.mp3"
    },
    "203": {
        "speaker": "PENGUIN",
        "character": "すみません　大きいな声出して",
        "definition": "I'm sorry for being so loud!",
        "timestamp": "0:15:41",
        "audio": "/audio/15/0.15.41.mp3"
    },
    "204": {
        "speaker": "PENKO",
        "character": "いいえ　いつもありがとうございます",
        "definition": "No, thank you for coming by all the time.",
        "timestamp": "0:15:44",
        "audio": "/audio/15/0.15.44.mp3"
    },
    "205": {
        "speaker": "PENGUIN",
        "character": "いえ　そんな大したこと",
        "definition": "I-It's no big deal.",
        "timestamp": "0:15:48",
        "audio": "/audio/15/0.15.48.mp3"
    },
    "206": {
        "speaker": "PENKO",
        "character": "分かります　すごく好きなんだなって",
        "definition": "I can tell that you're in love...",
        "timestamp": "0:15:51",
        "audio": "/audio/15/0.15.51.mp3"
    },
    "207": {
        "speaker": "PENKO",
        "character": "パンが",
        "definition": "with the bread.",
        "timestamp": "0:15:58",
        "audio": "/audio/15/0.15.58.mp3"
    },
    "208": {
        "speaker": "PENKO",
        "character": "ありがとうございました",
        "definition": "Thank you very much!",
        "timestamp": "0:16:02",
        "audio": "/audio/15/0.16.02.mp3"
    },
    "209": {
        "speaker": "PENGUIN",
        "character": "あのう",
        "definition": "Um...",
        "timestamp": "0:16:06",
        "audio": "/audio/15/0.16.06.mp3"
    },
    "210": {
        "speaker": "PENKO",
        "character": "はい",
        "definition": "Yes?",
        "timestamp": "0:16:07",
        "audio": "/audio/15/0.16.07.mp3"
    },
    "211": {
        "speaker": "PENGUIN",
        "character": "前からあなたの事が好きでした",
        "definition": "I've always liked you!",
        "timestamp": "0:16:10",
        "audio": "/audio/15/0.16.10.mp3"
    },
    "212": {
        "speaker": "PENGUIN",
        "character": "僕とデートしてください",
        "definition": "Please go on a date with me!",
        "timestamp": "0:16:12",
        "audio": "/audio/15/0.16.12.mp3"
    },
    "213": {
        "speaker": "PENGUIN",
        "character": "日曜日駅前で一時にまってます",
        "definition": "I'll be waiting in front of the station on Sunday at 1 PM! Huh?",
        "timestamp": "0:16:14",
        "audio": "/audio/15/0.16.14.mp3"
    },
    "214": {
        "speaker": "",
        "character": "それじゃ",
        "definition": "'Kay, bye!",
        "timestamp": "0:16:17",
        "audio": "/audio/15/0.16.17.mp3"
    },
    "215": {
        "speaker": "SASAKO",
        "character": "あれからペンギンさん　毎日パン屋さんに行ってデートに誘ってるらしいですよ",
        "definition": "Apparently, Mr. Penguin has been asking her out every day since then. Today's the fourth day in a row.",
        "timestamp": "0:16:25",
        "audio": "/audio/15/0.16.25.mp3"
    },
    "216": {
        "speaker": "SASAKO",
        "character": "ＯＫもらうまで通うって",
        "definition": "Apparently he's going to keep trying until he gets a yes.",
        "timestamp": "0:16:33",
        "audio": "/audio/15/0.16.33.mp3"
    },
    "217": {
        "speaker": "PANDA",
        "character": "しつこくない",
        "definition": "Isn't that a little pushy?",
        "timestamp": "0:16:35",
        "audio": "/audio/15/0.16.35.mp3"
    },
    "218": {
        "speaker": "SASAKO",
        "character": "そんなことないよ",
        "definition": "I don't think so.",
        "timestamp": "0:16:37",
        "audio": "/audio/15/0.16.37.mp3"
    },
    "219": {
        "speaker": "SASAKO",
        "character": "ペンギンさん頑張ってるよね",
        "definition": "Mr. Penguin's trying his best!",
        "timestamp": "0:16:39",
        "audio": "/audio/15/0.16.39.mp3"
    },
    "220": {
        "speaker": "POLAR BEAR",
        "character": "笹子さんは毎日毎日しつこく誘われたらどうなの",
        "definition": "How would you feel if someone asked you out persistently every day, Miss Sasako?",
        "timestamp": "0:16:43",
        "audio": "/audio/15/0.16.43.mp3"
    },
    "221": {
        "speaker": "SASAKO",
        "character": "え　それは嫌ですけど",
        "definition": "Huh? Well, I wouldn't like that...",
        "timestamp": "0:16:48",
        "audio": "/audio/15/0.16.48.mp3"
    },
    "222": {
        "speaker": "SASAKO",
        "character": "今日で一週間ですよ",
        "definition": "It's been a week today.",
        "timestamp": "0:17:39",
        "audio": "/audio/15/0.17.39.mp3"
    },
    "223": {
        "speaker": "SASAKO",
        "character": "幸せなんじゃないですかね",
        "definition": "It must feel nice, to have someone",
        "timestamp": "0:17:42",
        "audio": "/audio/15/0.17.42.mp3"
    },
    "224": {
        "speaker": "",
        "character": "こんなふうに一途に思われたら",
        "definition": "feel so strongly about just you.",
        "timestamp": "0:17:44",
        "audio": "/audio/15/0.17.44.mp3"
    },
    "225": {
        "speaker": "POLAR BEAR",
        "character": "そう",
        "definition": "Really?",
        "timestamp": "0:17:47",
        "audio": "/audio/15/0.17.47.mp3"
    },
    "226": {
        "speaker": "SASAKO",
        "character": "そうですよ",
        "definition": "Of course!",
        "timestamp": "0:17:48",
        "audio": "/audio/15/0.17.48.mp3"
    },
    "227": {
        "speaker": "PANDA",
        "character": "笹子さんは一週間　毎日毎日しつこくされるのはどうなの",
        "definition": "How would you feel if someone persistently asked you out every day for a week, Miss Sasako?",
        "timestamp": "0:17:50",
        "audio": "/audio/15/0.17.50.mp3"
    },
    "228": {
        "speaker": "SASAKO",
        "character": "それは嫌ですけど",
        "definition": "Well, I wouldn't like that...",
        "timestamp": "0:18:01",
        "audio": "/audio/15/0.18.01.mp3"
    },
    "229": {
        "speaker": "PENGUIN",
        "character": "前からあなたの事が好きでした",
        "definition": "I've always liked you!",
        "timestamp": "0:18:15",
        "audio": "/audio/15/0.18.15.mp3"
    },
    "230": {
        "speaker": "PENGUIN",
        "character": "僕とデートしてください",
        "definition": "Please go on a date with me!",
        "timestamp": "0:18:17",
        "audio": "/audio/15/0.18.17.mp3"
    },
    "231": {
        "speaker": "PENGUIN",
        "character": "日曜日駅前で一時にまってます",
        "definition": "I'll be waiting in front of the station on Sunday at 1 PM!",
        "timestamp": "0:18:19",
        "audio": "/audio/15/0.18.19.mp3"
    },
    "232": {
        "speaker": "PENKO",
        "character": "日曜日って明日ですよね",
        "definition": "Tomorrow is Sunday, right?",
        "timestamp": "0:18:24",
        "audio": "/audio/15/0.18.24.mp3"
    },
    "233": {
        "speaker": "PENGUIN",
        "character": "うん　はい　急ですね　すみません",
        "definition": "Uh, yes! I'm sorry, it's rather sudden.",
        "timestamp": "0:18:26",
        "audio": "/audio/15/0.18.26.mp3"
    },
    "234": {
        "speaker": "PENKO",
        "character": "分かりました",
        "definition": "Okay.",
        "timestamp": "0:18:31",
        "audio": "/audio/15/0.18.31.mp3"
    },
    "235": {
        "speaker": "PENGUIN",
        "character": "え？",
        "definition": "Huh?",
        "timestamp": "0:18:33",
        "audio": "/audio/15/0.18.33.mp3"
    },
    "236": {
        "speaker": "PENGUIN",
        "character": "僕らはね　最初から愛し合っていたんじゃないかな",
        "definition": "I think that we both loved each other from the start.",
        "timestamp": "0:18:40",
        "audio": "/audio/15/0.18.40.mp3"
    },
    "237": {
        "speaker": "PENGUIN",
        "character": "一週間毎日パン屋さんに行って　告白をしたわけだよ",
        "definition": "I went to the bakery every day for weekand kept asking her out. I see...",
        "timestamp": "0:18:45",
        "audio": "/audio/15/0.18.45.mp3"
    },
    "238": {
        "speaker": "PENGUIN",
        "character": "でね　とうとう一週間目のことだよ",
        "definition": "And then on the last day of that week...",
        "timestamp": "0:18:51",
        "audio": "/audio/15/0.18.51.mp3"
    },
    "239": {
        "speaker": "PENGUIN",
        "character": "それでさ　ペン美ちゃんがね",
        "definition": "That's when Penmi...",
        "timestamp": "0:18:54",
        "audio": "/audio/15/0.18.54.mp3"
    },
    "240": {
        "speaker": "PENGUIN",
        "character": "あ　彼女ペン子ちゃんじゃなくて　ペン美ちゃんって名前だったんだけど",
        "definition": "Oh, her name is Penmi, not Penko.",
        "timestamp": "0:18:56",
        "audio": "/audio/15/0.18.56.mp3"
    },
    "241": {
        "speaker": "PENGUIN",
        "character": "ペン美ちゃんがどうしたって聞いてみて",
        "definition": "You should totally ask me what Penmi did next. This is the fifth time.",
        "timestamp": "0:19:01",
        "audio": "/audio/15/0.19.01.mp3"
    },
    "242": {
        "speaker": "SASAKO",
        "character": "聞いたほうがいいんですか",
        "definition": "Should we really ask again?",
        "timestamp": "0:19:07",
        "audio": "/audio/15/0.19.07.mp3"
    },
    "243": {
        "speaker": "PENGUIN",
        "character": "だから　ペン美ちゃんがどうしたか聞いてみて",
        "definition": "Ask me what Penmi did next.",
        "timestamp": "0:19:10",
        "audio": "/audio/15/0.19.10.mp3"
    },
    "244": {
        "speaker": "SASAKO",
        "character": "ペン美ちゃんがどうしたんですか？",
        "definition": "So what did Penmi do?",
        "timestamp": "0:19:14",
        "audio": "/audio/15/0.19.14.mp3"
    },
    "245": {
        "speaker": "PENGUIN",
        "character": "日曜日って明日ですかって聞いてきたの",
        "definition": "She asked, \"Tomorrow is Sunday, right?\"",
        "timestamp": "0:19:16",
        "audio": "/audio/15/0.19.16.mp3"
    },
    "246": {
        "speaker": "PANDA",
        "character": "もう分かったよ",
        "definition": "We got it.",
        "timestamp": "0:19:20",
        "audio": "/audio/15/0.19.20.mp3"
    },
    "247": {
        "speaker": "PENGUIN",
        "character": "きっと僕たちは　愛し合う運命だったんだよ",
        "definition": "It was fate for us to fall in love with each other.",
        "timestamp": "0:19:22",
        "audio": "/audio/15/0.19.22.mp3"
    },
    "248": {
        "speaker": "PENGUIN",
        "character": "あ　パン食べて　いいから　遠慮なく食べて",
        "definition": "Oh, have some bread. No need to hold back, dig in!",
        "timestamp": "0:19:26",
        "audio": "/audio/15/0.19.26.mp3"
    },
    "249": {
        "speaker": "PENGUIN",
        "character": "じゃ　また明日～",
        "definition": "Well, then, see you again tomorrow!",
        "timestamp": "0:19:29",
        "audio": "/audio/15/0.19.29.mp3"
    },
    "250": {
        "speaker": "PANDA",
        "character": "明日は何回聞けばいいのかな",
        "definition": "I wonder how many times we'll have to ask him tomorrow.",
        "timestamp": "0:19:35",
        "audio": "/audio/15/0.19.35.mp3"
    },
    "251": {
        "speaker": "POLAR BEAR",
        "character": "20回くらい",
        "definition": "Probably around twenty.",
        "timestamp": "0:19:39",
        "audio": "/audio/15/0.19.39.mp3"
    },
    "252": {
        "speaker": "PENGUIN",
        "character": "ペン美ちゃんまだかな",
        "definition": "I wonder if Penmi is here yet.",
        "timestamp": "0:19:51",
        "audio": "/audio/15/0.19.51.mp3"
    },
    "253": {
        "speaker": "PENGUIN",
        "character": "まだちょっと早かったかな",
        "definition": "Maybe I was a little early.",
        "timestamp": "0:19:54",
        "audio": "/audio/15/0.19.54.mp3"
    },
    "254": {
        "speaker": "PENGUIN",
        "character": "ペン美ちゃん",
        "definition": "Penmi!",
        "timestamp": "0:19:59",
        "audio": "/audio/15/0.19.59.mp3"
    },
    "255": {
        "speaker": "PENGUIN",
        "character": "おい　ペン美ちゃん",
        "definition": "Hey, Penmi!",
        "timestamp": "0:20:01",
        "audio": "/audio/15/0.20.01.mp3"
    },
    "256": {
        "speaker": "PENKO",
        "character": "え　あたしペン子だけど",
        "definition": "What? My name is Penko.",
        "timestamp": "0:20:07",
        "audio": "/audio/15/0.20.07.mp3"
    },
    "257": {
        "speaker": "PENGUIN",
        "character": "え",
        "definition": "Huh?",
        "timestamp": "0:20:09",
        "audio": "/audio/15/0.20.09.mp3"
    },
    "258": {
        "speaker": "PENKA",
        "character": "ちょっと　どういうこと？",
        "definition": "What's going on?",
        "timestamp": "0:20:10",
        "audio": "/audio/15/0.20.10.mp3"
    },
    "259": {
        "speaker": "PENGUIN",
        "character": "え！ペン美ちゃんがもう一人",
        "definition": "What?! Another Penmi?!",
        "timestamp": "0:20:12",
        "audio": "/audio/15/0.20.12.mp3"
    },
    "260": {
        "speaker": "PENKA",
        "character": "何言ってるの　わたし　ペン花よ",
        "definition": "What are you talking about? My name is Penka! Huh?!",
        "timestamp": "0:20:15",
        "audio": "/audio/15/0.20.15.mp3"
    },
    "261": {
        "speaker": "PENNA",
        "character": "ちょっとあんた　あたしのこと好きだったんじゃないの",
        "definition": "Hey, I thought you said you loved me!",
        "timestamp": "0:20:20",
        "audio": "/audio/15/0.20.20.mp3"
    },
    "262": {
        "speaker": "PENGUIN",
        "character": "あれ　君がペン美ちゃん？",
        "definition": "What the?! Are you Penmi? I'm Penna!",
        "timestamp": "0:20:24",
        "audio": "/audio/15/0.20.24.mp3"
    },
    "263": {
        "speaker": "PENNO",
        "character": "ペン乃よ",
        "definition": "I'm Penno!",
        "timestamp": "0:20:28",
        "audio": "/audio/15/0.20.28.mp3"
    },
    "264": {
        "speaker": "PENJOLINA",
        "character": "どういうこと？",
        "definition": "What's the meaning of this? Y-You've got it all wrong, Penmi!",
        "timestamp": "0:20:30",
        "audio": "/audio/15/0.20.30.mp3"
    },
    "265": {
        "speaker": "PENJOLINA",
        "character": "ペンジョリナよ",
        "definition": "I'm Penjolina.",
        "timestamp": "0:20:33",
        "audio": "/audio/15/0.20.33.mp3"
    },
    "266": {
        "speaker": "PENGUIN",
        "character": "ペンジョリナ",
        "definition": "Penjolina?",
        "timestamp": "0:20:36",
        "audio": "/audio/15/0.20.36.mp3"
    },
    "267": {
        "speaker": "PENUELLE",
        "character": "ちょっと　ペンギンさん",
        "definition": "Hey, Mr. Penguin.",
        "timestamp": "0:20:38",
        "audio": "/audio/15/0.20.38.mp3"
    },
    "268": {
        "speaker": "PENGUIN",
        "character": "ごめんペン美ちゃん",
        "definition": "I'm sorry, Penmi. This is...",
        "timestamp": "0:20:39",
        "audio": "/audio/15/0.20.39.mp3"
    },
    "269": {
        "speaker": "PENUELLE",
        "character": "ペンニュエルよ",
        "definition": "I'm Penuelle.",
        "timestamp": "0:20:42",
        "audio": "/audio/15/0.20.42.mp3"
    },
    "270": {
        "speaker": "PENGUIN",
        "character": "ペンニュエル！",
        "definition": "Penuelle?!",
        "timestamp": "0:20:43",
        "audio": "/audio/15/0.20.43.mp3"
    },
    "271": {
        "speaker": "PENMI",
        "character": "ペンギンさん",
        "definition": "Mr. Penguin.",
        "timestamp": "0:20:44",
        "audio": "/audio/15/0.20.44.mp3"
    },
    "272": {
        "speaker": "PENGUIN",
        "character": "はい",
        "definition": "Yes?!",
        "timestamp": "0:20:45",
        "audio": "/audio/15/0.20.45.mp3"
    },
    "273": {
        "speaker": "PENMI",
        "character": "あたしがペン美よ",
        "definition": "I'm Penmi.",
        "timestamp": "0:20:46",
        "audio": "/audio/15/0.20.46.mp3"
    },
    "274": {
        "speaker": "PENMI",
        "character": "どういうこと？",
        "definition": "What's the meaning of this? Um... I'm not sure myself.",
        "timestamp": "0:20:48",
        "audio": "/audio/15/0.20.48.mp3"
    },
    "275": {
        "speaker": "GIRLS",
        "character": "どういうこと？",
        "definition": "What's the meaning of this?! P-Penmi!",
        "timestamp": "0:20:57",
        "audio": "/audio/15/0.20.57.mp3"
    },
    "276": {
        "speaker": "PENGUIN",
        "character": "ペ　ペン乃ちゃん",
        "definition": "Penno! Stop!",
        "timestamp": "0:21:02",
        "audio": "/audio/15/0.21.02.mp3"
    },
    "277": {
        "speaker": "PENGUIN",
        "character": "ペン美ちゃん　ペン美ちゃん　助けて",
        "definition": "Penmi! Penmi! Help!",
        "timestamp": "0:21:07",
        "audio": "/audio/15/0.21.07.mp3"
    },
    "278": {
        "speaker": "PENGUIN",
        "character": "まさか七人いるなんて思わなかった",
        "definition": "I never would have thought there were seven of them.",
        "timestamp": "0:21:13",
        "audio": "/audio/15/0.21.13.mp3"
    },
    "279": {
        "speaker": "PENGUIN",
        "character": "毎日違う子に告白してたなんて",
        "definition": "I had no idea I was asking out someone different each day.",
        "timestamp": "0:21:17",
        "audio": "/audio/15/0.21.17.mp3"
    },
    "280": {
        "speaker": "POLAR BEAR",
        "character": "パン屋さんのシフトのせいだ",
        "definition": "It's because of the shifts at the bakery. Curse those shifts.",
        "timestamp": "0:21:20",
        "audio": "/audio/15/0.21.20.mp3"
    },
    "281": {
        "speaker": "PENGUIN",
        "character": "行くよ",
        "definition": "I'm leaving.",
        "timestamp": "0:21:33",
        "audio": "/audio/15/0.21.33.mp3"
    },
    "282": {
        "speaker": "SASAKO",
        "character": "もう",
        "definition": "Already? I can feel their presence.",
        "timestamp": "0:21:34",
        "audio": "/audio/15/0.21.34.mp3"
    },
    "283": {
        "speaker": "PENGUIN",
        "character": "じゃ",
        "definition": "See ya!",
        "timestamp": "0:21:41",
        "audio": "/audio/15/0.21.41.mp3"
    },
    "284": {
        "speaker": "PANDA",
        "character": "ペンギンさん　告白できてよかったね",
        "definition": "It's good that Mr. Penguin was finally able to confess.",
        "timestamp": "0:21:57",
        "audio": "/audio/15/0.21.57.mp3"
    },
    "285": {
        "speaker": "SASAKO",
        "character": "これで　良かったんですかね",
        "definition": "I wonder if this is how it should have ended up.",
        "timestamp": "0:22:01",
        "audio": "/audio/15/0.22.01.mp3"
    },
    "286": {
        "speaker": "POLAR BEAR",
        "character": "笹子さんは　毎日毎日しつこくノロケ話を聞かされるのってどうなの",
        "definition": "How would you feel if you had to listen to someone gush about their loved one every day?",
        "timestamp": "0:22:05",
        "audio": "/audio/15/0.22.05.mp3"
    },
    "287": {
        "speaker": "SASAKO",
        "character": "さあー",
        "definition": "Not sure.",
        "timestamp": "0:22:15",
        "audio": "/audio/15/0.22.15.mp3"
    },
    "288": {
        "speaker": "PANDA",
        "character": "ペンギンさん　ペンギンさん",
        "definition": "Mr. Penguin, Mr. Penguin!",
        "timestamp": "0:23:57",
        "audio": "/audio/15/0.23.57.mp3"
    },
    "289": {
        "speaker": "PENGUIN",
        "character": "何　パンダ君",
        "definition": "What is it, Panda?",
        "timestamp": "0:23:59",
        "audio": "/audio/15/0.23.59.mp3"
    },
    "290": {
        "speaker": "PANDA",
        "character": "なんか落ち着かないね",
        "definition": "I feel rather uneasy.",
        "timestamp": "0:24:00",
        "audio": "/audio/15/0.24.00.mp3"
    },
    "291": {
        "speaker": "PENGUIN",
        "character": "そう？",
        "definition": "Really?",
        "timestamp": "0:24:02",
        "audio": "/audio/15/0.24.02.mp3"
    },
    "292": {
        "speaker": "PANDA",
        "character": "ペンギンさんに何か不吉なことが起きなければいいけど",
        "definition": "I hope nothing bad happens to you, Mr. Penguin.",
        "timestamp": "0:24:03",
        "audio": "/audio/15/0.24.03.mp3"
    },
    "293": {
        "speaker": "PENGUIN",
        "character": "僕限定",
        "definition": "This is reserved just for me?",
        "timestamp": "0:24:06",
        "audio": "/audio/15/0.24.06.mp3"
    },
    "294": {
        "speaker": "PANDA",
        "character": "もしかしてペンギンさん　プチじゃない整形した",
        "definition": "Could it be that you had some work done that's not minor?",
        "timestamp": "0:24:07",
        "audio": "/audio/15/0.24.07.mp3"
    },
    "295": {
        "speaker": "PENGUIN",
        "character": "してません　けどなんか落ち着かないね",
        "definition": "I have not. However, I'm feeling a bit uneasy, too.",
        "timestamp": "0:24:10",
        "audio": "/audio/15/0.24.10.mp3"
    },
    "296": {
        "speaker": "PENGUIN",
        "character": "白熊君　終わろ",
        "definition": "Let's end this, Polar Bear.",
        "timestamp": "0:24:13",
        "audio": "/audio/15/0.24.13.mp3"
    },
    "297": {
        "speaker": "POLAR BEAR",
        "character": "来週のしろくまカフェは",
        "definition": "Next week's Polar Bear's Café,",
        "timestamp": "0:24:14",
        "audio": "/audio/15/0.24.14.mp3"
    },
    "298": {
        "speaker": "POLAR BEAR",
        "character": "50倍でお送りします",
        "definition": "will be fifty times bigger in size.",
        "timestamp": "0:24:16",
        "audio": "/audio/15/0.24.16.mp3"
    },
    "299": {
        "speaker": "PENGUIN",
        "character": "何が　何が50倍なの",
        "definition": "What is? What's going to be fifty times bigger? Miss Sasako, end it, please.",
        "timestamp": "0:24:18",
        "audio": "/audio/15/0.24.18.mp3"
    },
    "300": {
        "speaker": "SASAKO",
        "character": "お楽しみに",
        "definition": "Enjoy!",
        "timestamp": "0:24:22",
        "audio": "/audio/15/0.24.22.mp3"
    }
}